{
  "project_info": {
    "project_number": "560036982005",
    "project_id": "adhd-101",
    "storage_bucket": "adhd-101.appspot.com"
  },
  "client": [
    {
      "client_info": {
        "mobilesdk_app_id": "1:560036982005:android:7b74fb39fcdf6bc041e9bc",
        "android_client_info": {
          "package_name": "com.wkowus2.ADHDProject"
        }
      },
      "oauth_client": [
        {
          "client_id": "560036982005-7kofsnh1to64l0ma1269qndef46ih5cc.apps.googleusercontent.com",
          "client_type": 1,
          "android_info": {
            "package_name": "com.wkowus2.ADHDProject",
            "certificate_hash": "5e8f16062ea3cd2c4a0d547876baa6f38cabf625"
          }
        },
        {
          "client_id": "560036982005-o0hbsr2q6t3ka09edld3s631fgu6vb64.apps.googleusercontent.com",
          "client_type": 3
        }
      ],
      "api_key": [
        {
          "current_key": "AIzaSyASkhUwmeTEAsRx6TjWJUpI7s0aQ_3Rma8"
        }
      ],
      "services": {
        "appinvite_service": {
          "other_platform_oauth_client": [
            {
              "client_id": "560036982005-o0hbsr2q6t3ka09edld3s631fgu6vb64.apps.googleusercontent.com",
              "client_type": 3
            }
          ]
        }
      }
    }
  ],
  "configuration_version": "1"
}